fimm/train.py
fimm/validate.py
fimm/custom/timm/data/__init__.py
fimm/custom/timm/data/loader.py
fimm/custom/timm/data/transforms_factory.py
fimm/custom/timm/utils/__init__.py
fimm/custom/timm/utils/checkpoint_saver.py
fimm/finetuning/utils.py
fimm/finetuning/strategies/__init__.py
fimm/finetuning/strategies/normalization/__init__.py
fimm/finetuning/strategies/normalization/stochnorm.py
fimm/finetuning/strategies/regularization/__init__.py
fimm/finetuning/strategies/regularization/bss.py
fimm/finetuning/strategies/regularization/co_tuning.py
fimm/finetuning/strategies/regularization/delta.py
fimm-0.0.3.dist-info/LICENSE
fimm-0.0.3.dist-info/METADATA
fimm-0.0.3.dist-info/WHEEL
fimm-0.0.3.dist-info/entry_points.txt
fimm-0.0.3.dist-info/top_level.txt
fimm-0.0.3.dist-info/RECORD
