Metadata-Version: 2.1
Name: fimm
Version: 0.0.3
Summary: Finetune PyTorch Image Models with TIMM
Author-email: Ivo Rapant <rapanti@cs.uni-freiburg.de>
License: MIT License
Project-URL: Homepage, https://github.com/rapanti/fimm
Project-URL: Bug Reports, https://github.com/rapanti/fimm/issues
Project-URL: Source, https://github.com/rapanti/fimm
Keywords: Machine Learning,Deep Learning,Image,Fine-Tuning
Classifier: Development Status :: 4 - Beta
Classifier: Intended Audience :: Developers
Classifier: Intended Audience :: Science/Research
Classifier: License :: OSI Approved :: BSD License
Classifier: Operating System :: Unix
Classifier: Programming Language :: Python
Classifier: Programming Language :: Python :: 3.11
Classifier: Topic :: Software Development :: Build Tools
Requires-Python: >=3.11
License-File: LICENSE
Requires-Dist: timm
